shapps/__init__.py
shapps/auth/__init__.py
shapps/auth/apiuser/__init__.py
shapps/auth/apiuser/middle_apiuser.py
shapps/auth/apiuser/views.py
shapps/auth/ipuser/__init__.py
shapps/auth/ipuser/commands.py
shapps/auth/ipuser/conf.py
shapps/auth/ipuser/middle_ipuser.py
shapps/auth/ipuser_admin/__init__.py
shapps/auth/ipuser_admin/conf.py
shapps/auth/ipuser_admin/views.py
shapps/auth/ldap/__init__.py
shapps/auth/ldap/conf.py
shapps/auth/ldap/ldap_login.py
shapps/auth/lenovoid/__init__.py
shapps/auth/lenovoid/middle_lenovoid.py
shapps/auth/lenovoid/models.py
shapps/auth/lenovoid/views.py
shapps/auth/orgrbac/__init__.py
shapps/auth/orgrbac/conf.py
shapps/auth/orgrbac/dbinit.py
shapps/auth/orgrbac/models.py
shapps/auth/orgrbac/orgrbac.py
shapps/auth/orgrbac_admin/__init__.py
shapps/auth/orgrbac_admin/conf.py
shapps/auth/orgrbac_admin/views.py
shapps/auth/superuser/__init__.py
shapps/auth/superuser/commands.py
shapps/auth/superuser/conf.py
shapps/auth/usercmd/__init__.py
shapps/auth/usercmd/commands.py
shapps/auth/xforwardedfor/__init__.py
shapps/auth/xforwardedfor/conf.py
shapps/auth/xforwardedfor/middle_xforwardedfor.py
shapps/filedir/__init__.py
shapps/filedir/sharedir/__init__.py
shapps/filedir/sharedir/conf.py
shapps/filedir/sharedir/views.py
shapps/linci/__init__.py
shapps/linci/artifact/__init__.py
shapps/linci/artifact/models.py
shapps/linci/artifact/views.py
shapps/ui/__init__.py
shapps/ui/ace/__init__.py
shapps/ui/ace/conf.py
shapps/ui/ace/config.ini
shapps/ui/ace/info.ini
shapps/ui/ace/settings.ini
shapps/ui/ace/static/readme.txt
shapps/ui/ace/static/ace/1.0.0/ace-elements.min.js
shapps/ui/ace/static/ace/1.0.0/ace.min.css
shapps/ui/ace/static/ace/1.0.0/ace.min.js
shapps/ui/ace/static/ace/1.0.0/bootbox.min.js
shapps/ui/ace/static/ace/1.0.0/jquery.dataTables.bootstrap.js
shapps/ui/ace/static/ace/1.0.0/readme.txt
shapps/ui/ace/template_plugins/__init__.py
shapps/ui/ace/template_plugins/ace.py
shapps/ui/ace/templates/readme.txt
shapps/ui/bootstrap/__init__.py
shapps-0.1.1.dist-info/METADATA
shapps-0.1.1.dist-info/WHEEL
shapps-0.1.1.dist-info/entry_points.txt
shapps-0.1.1.dist-info/top_level.txt
shapps-0.1.1.dist-info/RECORD
