Metadata-Version: 2.1
Name: shapps
Version: 0.1.1
Summary: Another apps collection for uliweb
Home-page: https://github.com/zhangchunlin/shapps
Author: Chunlin Zhang
Author-email: zhangchunlin@gmail.com
License: BSD
Keywords: wsgi web framework
Platform: any
Classifier: Development Status :: 2 - Pre-Alpha
Classifier: Intended Audience :: Developers
Classifier: License :: OSI Approved :: BSD License
Classifier: Topic :: Internet :: WWW/HTTP :: WSGI
Classifier: Programming Language :: Python
Classifier: Operating System :: OS Independent
Classifier: Programming Language :: Python :: 2.6
Classifier: Programming Language :: Python :: 2.7
